README.md
setup.py
t2epub/__init__.py
t2epub/main.py
t2epub/processor.py
t2epub/templates.py
t2epub/utilitis.py
t2epub.egg-info/PKG-INFO
t2epub.egg-info/SOURCES.txt
t2epub.egg-info/dependency_links.txt
t2epub.egg-info/entry_points.txt
t2epub.egg-info/requires.txt
t2epub.egg-info/top_level.txt
t2epub.egg-info/zip-safe