Metadata-Version: 1.0
Name: t2epub
Version: 0.0.1
Summary: Commnadline tool to transfer txt file to epub format
Home-page: https://github.com/ipconfiger/t2epub
Author: Alexander Li
Author-email: superpowerlee@gmail.com
License: GNU General Public License v3.0
Keywords: txt epub novel
Platform: UNKNOWN
